epmc_serial/__init__.py
epmc_serial/epmc_serial.py
epmc_serial-1.2.0.dist-info/licenses/LICENSE
epmc_serial-1.2.0.dist-info/METADATA
epmc_serial-1.2.0.dist-info/WHEEL
epmc_serial-1.2.0.dist-info/top_level.txt
epmc_serial-1.2.0.dist-info/RECORD
