Metadata-Version: 2.4
Name: epmc-serial
Version: 1.2.0
Summary: Python serial interface for the Easy PID Motor Controller (EPMC)
Author-email: Samuel Obiagba <samuel.c.agba@gmail.com>
License-Expression: MIT
Classifier: Programming Language :: Python :: 3
Classifier: Operating System :: OS Independent
Requires-Python: >=3.8
License-File: LICENSE
Requires-Dist: pyserial
Dynamic: license-file
